mplleaflet/__init__.py
mplleaflet/_display.py
mplleaflet/leaflet_renderer.py
mplleaflet/links.py
mplleaflet/maptiles.py
mplleaflet/utils.py
mplleaflet/mplexporter/__init__.py
mplleaflet/mplexporter/_py3k_compat.py
mplleaflet/mplexporter/exporter.py
mplleaflet/mplexporter/tools.py
mplleaflet/mplexporter/utils.py
mplleaflet/mplexporter/renderers/__init__.py
mplleaflet/mplexporter/renderers/base.py
mplleaflet/mplexporter/renderers/fake_renderer.py
mplleaflet/mplexporter/renderers/vega_renderer.py
mplleaflet/mplexporter/renderers/vincent_renderer.py
mplleaflet/mplexporter/tests/__init__.py
mplleaflet/mplexporter/tests/test_basic.py
mplleaflet/mplexporter/tests/test_utils.py
mplleaflet/templates/__init__.py
mplleaflet/templates/base.html
mplleaflet/templates/ipynb.html
mplleaflet_actual-0.0.6.dist-info/AUTHORS.md
mplleaflet_actual-0.0.6.dist-info/LICENSE.md
mplleaflet_actual-0.0.6.dist-info/METADATA
mplleaflet_actual-0.0.6.dist-info/WHEEL
mplleaflet_actual-0.0.6.dist-info/top_level.txt
mplleaflet_actual-0.0.6.dist-info/RECORD
