Metadata-Version: 2.1
Name: mplleaflet-actual
Version: 0.0.6
Summary: Convert Matplotlib plots into Leaflet web maps
Home-page: http://github.com/jwass/mplleaflet
Download-URL: http://github.com/jwass/mplleaflet
Author: Jacob Wasserman
Author-email: jwasserman@gmail.com
Maintainer: Jacob Wasserman
Maintainer-email: jwasserman@gmail.com
License: BSD 3-clause
License-File: LICENSE.md
License-File: AUTHORS.md
Requires-Dist: jinja2
Requires-Dist: six
